setup.py
django_blauwdruk/__init__.py
django_blauwdruk.egg-info/PKG-INFO
django_blauwdruk.egg-info/SOURCES.txt
django_blauwdruk.egg-info/dependency_links.txt
django_blauwdruk.egg-info/top_level.txt