Metadata-Version: 2.1
Name: django-blauwdruk
Version: 0.0.1
Summary: Django Blauwdruk
Home-page: UNKNOWN
Author: Klaas van Schelven
License: UNKNOWN
Platform: UNKNOWN
Requires-Python: >=3.7.*
